{
  "Learning_VBG": {
    "partOfSpeech": "Verb (gerund)",
    "definition": "The act of gaining knowledge or skills.",
    "image": "A person studying with books and a laptop.",
    "example": "Learning new things keeps your brain active."
  },
  "new_JJ": {
    "partOfSpeech": "Adjective",
    "definition": "Not existing before; recently created or discovered.",
    "image": "A shiny, unopened box.",
    "example": "She bought a new car last week."
  },
  "language_NN": {
    "partOfSpeech": "Noun",
    "definition": "A system of communication used by a community or country.",
    "image": "Speech bubbles in different languages.",
    "example": "French is a beautiful language."
  },
  "challenging_JJ": {
    "partOfSpeech": "Adjective",
    "definition": "Demanding effort or skill; difficult in a stimulating way.",
    "image": "A person climbing a steep hill.",
    "example": "The exam was very challenging."
  },
  "rewarding_JJ": {
    "partOfSpeech": "Adjective",
    "definition": "Providing satisfaction; worth the effort.",
    "image": "A trophy or a proud smile.",
    "example": "Helping others is a rewarding experience."
  },
  "journey_NN": {
    "partOfSpeech": "Noun",
    "definition": "An act of traveling from one place to another; often used metaphorically.",
    "image": "A long road leading into the horizon.",
    "example": "Learning English is a long journey."
  },
  "opens_VBZ": {
    "partOfSpeech": "Verb",
    "definition": "To make something accessible or available.",
    "image": "An open door with light shining through.",
    "example": "Education opens minds."
  },
  "doors_NNS": {
    "partOfSpeech": "Noun (plural)",
    "definition": "Metaphorical opportunities or possibilities.",
    "image": "Several doors labeled 'Career', 'Travel', 'Growth'.",
    "example": "Learning opens many doors."
  },
  "different_JJ": {
    "partOfSpeech": "Adjective",
    "definition": "Not the same as another or others.",
    "image": "People from various countries standing together.",
    "example": "He has friends from different cultures."
  },
  "cultures_NNS": {
    "partOfSpeech": "Noun (plural)",
    "definition": "The customs, beliefs, and way of life of a particular group of people.",
    "image": "Diverse cultural festivals and dress.",
    "example": "She enjoys learning about other cultures."
  },
  "perspectives_NNS": {
    "partOfSpeech": "Noun (plural)",
    "definition": "A particular way of thinking about something.",
    "image": "People looking at a cube from different angles.",
    "example": "Talking with others gives new perspectives."
  }
}